Task 4/Traffic_Light_Controller/traffic_light.v
module traffic_light(
    input clk,
    input reset,
    output reg [2:0] light
);

parameter RED    = 2'b00,
          GREEN  = 2'b01,
          YELLOW = 2'b10;

reg [1:0] state, next_state;

always @(posedge clk or posedge reset)
begin
    if (reset)
        state <= RED;
    else
        state <= next_state;
end

always @(*)
begin
    case (state)
        RED:    next_state = GREEN;
        GREEN:  next_state = YELLOW;
        YELLOW: next_state = RED;
        default: next_state = RED;
    endcase
end

always @(*)
begin
    case (state)
        RED:    light = 3'b100;   // Red ON
        GREEN:  light = 3'b001;   // Green ON
        YELLOW: light = 3'b010;   // Yellow ON
        default: light = 3'b100;
    endcase
end

endmodule

Task 4/Traffic_Light_Controller/tb_traffic_light.v
`timescale 1ns/1ps

module tb_traffic_light;

reg clk;
reg reset;
wire [2:0] light;


traffic_light uut (
    .clk(clk),
    .reset(reset),
    .light(light)
);


always #5 clk = ~clk;


initial
begin
    $dumpfile("traffic_light.vcd");
    $dumpvars(0, tb_traffic_light);
end

initial
begin
    clk = 0;
    reset = 1;

    #10 reset = 0;

    #60;

    $finish;
end

endmodule

Task 4/Traffic_Light_Controller/traffic_light.vcd
$date
	Mon Jul 20 10:33:46 2026
$end
$version
	Icarus Verilog
$end
$timescale
	1ps
$end
$scope module tb_traffic_light $end
$var wire 3 ! light [2:0] $end
$var reg 1 " clk $end
$var reg 1 # reset $end
$scope module uut $end
$var wire 1 " clk $end
$var wire 1 # reset $end
$var parameter 2 $ GREEN $end
$var parameter 2 % RED $end
$var parameter 2 & YELLOW $end
$var reg 3 ' light [2:0] $end
$var reg 2 ( next_state [1:0] $end
$var reg 2 ) state [1:0] $end
$upscope $end
$upscope $end
$enddefinitions $end
$comment Show the parameter values. $end
$dumpall
b10 &
b0 %
b1 $
$end
#0
$dumpvars
b0 )
b1 (
b100 '
1#
0"
b100 !
$end
#5000
1"
#10000
0"
0#
#15000
b10 (
b1 !
b1 '
b1 )
1"
#20000
0"
#25000
b10 !
b10 '
b0 (
b10 )
1"
#30000
0"
#35000
b1 (
b100 !
b100 '
b0 )
1"
#40000
0"
#45000
b1 !
b1 '
b10 (
b1 )
1"
#50000
0"
#55000
b0 (
b10 !
b10 '
b10 )
1"
#60000
0"
#65000
b100 !
b100 '
b1 (
b0 )
1"
