Task 4/Sequence_Detector/sequence_detector.v
module sequence_detector(
    input clk,
    input reset,
    input in,
    output reg detected
);

parameter S0 = 3'd0,
          S1 = 3'd1,
          S2 = 3'd2,
          S3 = 3'd3,
          S4 = 3'd4;

reg [2:0] state, next_state;

always @(posedge clk or posedge reset)
begin
    if(reset)
        state <= S0;
    else
        state <= next_state;
end

always @(*)
begin
    case(state)

        S0:
            if(in)
                next_state = S1;
            else
                next_state = S0;

        S1:
            if(in)
                next_state = S1;
            else
                next_state = S2;

        S2:
            if(in)
                next_state = S3;
            else
                next_state = S0;

        S3:
            if(in)
                next_state = S4;
            else
                next_state = S2;

        S4:
            if(in)
                next_state = S1;
            else
                next_state = S2;

        default:
            next_state = S0;

    endcase
end
 
always @(*)
begin
    if(state == S4)
        detected = 1'b1;
    else
        detected = 1'b0;
end

endmodule

Task 4/Sequence_Detector/tb_sequence_detector.v
`timescale 1ns/1ps

module tb_sequence_detector;

reg clk;
reg reset;
reg in;
wire detected;


sequence_detector uut (
    .clk(clk),
    .reset(reset),
    .in(in),
    .detected(detected)
);


always #5 clk = ~clk;


initial
begin
    $dumpfile("sequence_detector.vcd");
    $dumpvars(0, tb_sequence_detector);
end

initial
begin
    clk = 0;
    reset = 1;
    in = 0;

    #10 reset = 0;

    
    #10 in = 1;
    #10 in = 0;
    #10 in = 1;
    #10 in = 1;

    #20 in = 0;

    #20 $finish;
end

endmodule

Task 4/Sequence_Detector/sequence_detector.vcd
$date
	Mon Jul 20 10:50:59 2026
$end
$version
	Icarus Verilog
$end
$timescale
	1ps
$end
$scope module tb_sequence_detector $end
$var wire 1 ! detected $end
$var reg 1 " clk $end
$var reg 1 # in $end
$var reg 1 $ reset $end
$scope module uut $end
$var wire 1 " clk $end
$var wire 1 # in $end
$var wire 1 $ reset $end
$var parameter 3 % S0 $end
$var parameter 3 & S1 $end
$var parameter 3 ' S2 $end
$var parameter 3 ( S3 $end
$var parameter 3 ) S4 $end
$var reg 1 ! detected $end
$var reg 3 * next_state [2:0] $end
$var reg 3 + state [2:0] $end
$upscope $end
$upscope $end
$enddefinitions $end
$comment Show the parameter values. $end
$dumpall
b100 )
b11 (
b10 '
b1 &
b0 %
$end
#0
$dumpvars
b0 +
b0 *
1$
0#
0"
0!
$end
#5000
1"
#10000
0"
0$
#15000
1"
#20000
b1 *
0"
1#
#25000
b1 +
1"
#30000
b10 *
0"
0#
#35000
b0 *
b10 +
1"
#40000
b11 *
0"
1#
#45000
b100 *
b11 +
1"
#50000
0"
#55000
1!
b1 *
b100 +
1"
#60000
0"
#65000
0!
b1 +
1"
#70000
b10 *
0"
0#
#75000
b0 *
b10 +
1"
#80000
0"
#85000
b0 +
1"
