Task 4/Mealy_FSM/mealy_fsm.v
module mealy_fsm(
    input clk,
    input reset,
    input in,
    output reg out
);

reg state;

always @(posedge clk or posedge reset)
begin
    if (reset)
    begin
        state <= 0;
        out <= 0;
    end
    else
    begin
        case(state)

            0:
            begin
                if(in)
                begin
                    state <= 1;
                    out <= 0;
                end
            end

            1:
            begin
                if(in)
                begin
                    out <= 1;
                end
                else
                begin
                    state <= 0;
                    out <= 0;
                end
            end

        endcase
    end
end

endmodule

Task 4/Mealy_FSM/tb_mealy_fsm.v
`timescale 1ns/1ps

module tb_mealy_fsm;

reg clk;
reg reset;
reg in;
wire out;


mealy_fsm uut (
    .clk(clk),
    .reset(reset),
    .in(in),
    .out(out)
);

always #5 clk = ~clk;

initial
begin
    $dumpfile("mealy.vcd");
    $dumpvars(0, tb_mealy_fsm);
end

initial
begin
    clk = 0;
    reset = 1;
    in = 0;

    #10 reset = 0;

    #10 in = 1;
    #10 in = 1;
    #10 in = 0;
    #10 in = 1;
    #10 in = 1;

    #20 $finish;
end

endmodule

Task 4/Moore_FSM/mealy.vcd
$date
	Mon Jul 20 10:25:59 2026
$end
$version
	Icarus Verilog
$end
$timescale
	1ps
$end
$scope module tb_mealy_fsm $end
$var wire 1 ! out $end
$var reg 1 " clk $end
$var reg 1 # in $end
$var reg 1 $ reset $end
$scope module uut $end
$var wire 1 " clk $end
$var wire 1 # in $end
$var wire 1 $ reset $end
$var reg 1 ! out $end
$var reg 1 % state $end
$upscope $end
$upscope $end
$enddefinitions $end
$comment Show the parameter values. $end
$dumpall
$end
#0
$dumpvars
0%
1$
0#
0"
0!
$end
#5000
1"
#10000
0"
0$
#15000
1"
#20000
0"
1#
#25000
1%
1"
#30000
0"
#35000
1!
1"
#40000
0"
0#
#45000
0!
0%
1"
#50000
0"
1#
#55000
1%
1"
#60000
0"
#65000
1!
1"
