Task 4/Moore_FSM/moore_fsm.v
module moore_fsm(
    input clk,
    input reset,
    output reg y
);
parameter S0 = 2'b00,
          S1 = 2'b01,
          S2 = 2'b10;
reg [1:0] state, next_state;
always @(posedge clk or posedge reset)
begin
    if (reset)
        state <= S0;
    else
        state <= next_state;
end
always @(*)
begin
    case(state)
        S0: next_state = S1;
        S1: next_state = S2;
        S2: next_state = S0;
        default: next_state = S0;
    endcase
end
always @(*)
begin
    case(state)
        S0: y = 1'b0;
        S1: y = 1'b1;
        S2: y = 1'b0;
        default: y = 1'b0;
    endcase
end

endmodule

Task 4/Moore_FSM/tb_moore_fsm.v
`timescale 1ns/1ps

module tb_moore_fsm;

reg clk;
reg reset;
wire y;
moore_fsm uut (
    .clk(clk),
    .reset(reset),
    .y(y)
);
always #5 clk = ~clk;
initial
begin
    $dumpfile("moore.vcd");
    $dumpvars(0, tb_moore_fsm);
end
initial
begin
    clk = 0;
    reset = 1;

    #10;
    reset = 0;

    #60;

    $finish;
end

endmodule

Task 4/Moore_FSM/moore.vcd
$date
	Mon Jul 20 10:17:15 2026
$end
$version
	Icarus Verilog
$end
$timescale
	1ps
$end
$scope module tb_moore_fsm $end
$var wire 1 ! y $end
$var reg 1 " clk $end
$var reg 1 # reset $end
$scope module uut $end
$var wire 1 " clk $end
$var wire 1 # reset $end
$var parameter 2 $ S0 $end
$var parameter 2 % S1 $end
$var parameter 2 & S2 $end
$var reg 2 ' next_state [1:0] $end
$var reg 2 ( state [1:0] $end
$var reg 1 ! y $end
$upscope $end
$upscope $end
$enddefinitions $end
$comment Show the parameter values. $end
$dumpall
b10 &
b1 %
b0 $
$end
#0
$dumpvars
b0 (
b1 '
1#
0"
0!
$end
#5000
1"
#10000
0"
0#
#15000
b10 '
1!
b1 (
1"
#20000
0"
#25000
0!
b0 '
b10 (
1"
#30000
0"
#35000
b1 '
b0 (
1"
#40000
0"
#45000
1!
b10 '
b1 (
1"
#50000
0"
#55000
b0 '
0!
b10 (
1"
#60000
0"
#65000
b1 '
b0 (
1"
