Task 6/Processor/processor.v
module alu(
    input [3:0] A,
    input [3:0] B,
    input [2:0] sel,
    output reg [3:0] Y
);

always @(*) begin
    case(sel)
        3'b000: Y = A + B;   // ADD
        3'b001: Y = A - B;   // SUB
        3'b010: Y = A & B;   // AND
        3'b011: Y = A | B;   // OR
        3'b100: Y = A ^ B;   // XOR
        default: Y = 4'b0000;
    endcase
end

endmodule


module processor(
    input clk,
    input reset,
    input [7:0] instruction,
    output [3:0] result
);

wire [1:0] state;
wire [2:0] opcode;
wire [2:0] alu_op;
wire [3:0] A;
wire [3:0] B;

// Instruction fields
assign opcode = instruction[7:5];
assign A = {2'b00, instruction[4:3]};
assign B = {2'b00, instruction[2:1]};

// Control Unit
control_unit cu (
    .clk(clk),
    .reset(reset),
    .state(state)
);

// Instruction Decoder
decoder d1 (
    .opcode(opcode),
    .alu_op(alu_op)
);

// ALU
alu a1 (
    .A(A),
    .B(B),
    .sel(alu_op),
    .Y(result)
);

endmodule

Task 6/Instruction_Decoder/decoder.v
module decoder(
    input [2:0] opcode,
    output reg [2:0] alu_op
);

always @(*) begin
    case(opcode)
        3'b000: alu_op = 3'b000; // ADD
        3'b001: alu_op = 3'b001; // SUB
        3'b010: alu_op = 3'b010; // AND
        3'b011: alu_op = 3'b011; // OR
        default: alu_op = 3'b000;
    endcase
end

endmodule

Task 6/Control_Unit/control_unit.v
module control_unit(
    input clk,
    input reset,
    output reg [1:0] state
);

parameter FETCH   = 2'b00,
          DECODE  = 2'b01,
          EXECUTE = 2'b10;

always @(posedge clk or posedge reset) begin
    if (reset)
        state <= FETCH;
    else begin
        case(state)
            FETCH:   state <= DECODE;
            DECODE:  state <= EXECUTE;
            EXECUTE: state <= FETCH;
            default: state <= FETCH;
        endcase
    end
end

endmodule

Task 6/Processor/tb_processor.v
`timescale 1ns/1ps

module tb_processor;

reg clk;
reg reset;
reg [7:0] instruction;
wire [3:0] result;

processor uut (
    .clk(clk),
    .reset(reset),
    .instruction(instruction),
    .result(result)
);

// Clock generation
always #5 clk = ~clk;

initial begin
    $dumpfile("processor.vcd");
    $dumpvars(0, tb_processor);

    clk = 0;
    reset = 1;
    instruction = 8'b00000000;

    // Apply reset
    #10;
    reset = 0;

    // ADD: A=3, B=2
    instruction = 8'b00011100;
    #10;

     // SUB: A=3, B=1
    instruction = 8'b00111010;
    #10;

    // AND: A=2, B=1
    instruction = 8'b01010010;
    #10;

    // OR: A=3, B=1
    instruction = 8'b01111010;
    #10;

    $finish;
end

endmodule

Task 6/Processor/processor.vcd
$date
	Thu Sep 10 11:07:01 2026
$end
$version
	Icarus Verilog
$end
$timescale
	1ps
$end
$scope module tb_processor $end
$var wire 4 ! result [3:0] $end
$var reg 1 " clk $end
$var reg 8 # instruction [7:0] $end
$var reg 1 $ reset $end
$scope module uut $end
$var wire 1 " clk $end
$var wire 8 % instruction [7:0] $end
$var wire 1 $ reset $end
$var wire 2 & state [1:0] $end
$var wire 4 ' result [3:0] $end
$var wire 3 ( opcode [2:0] $end
$var wire 3 ) alu_op [2:0] $end
$var wire 4 * B [3:0] $end
$var wire 4 + A [3:0] $end
$scope module a1 $end
$var wire 4 , A [3:0] $end
$var wire 4 - B [3:0] $end
$var wire 3 . sel [2:0] $end
$var reg 4 / Y [3:0] $end
$upscope $end
$scope module cu $end
$var wire 1 " clk $end
$var wire 1 $ reset $end
$var parameter 2 0 DECODE $end
$var parameter 2 1 EXECUTE $end
$var parameter 2 2 FETCH $end
$var reg 2 3 state [1:0] $end
$upscope $end
$scope module d1 $end
$var wire 3 4 opcode [2:0] $end
$var reg 3 5 alu_op [2:0] $end
$upscope $end
$upscope $end
$upscope $end
$enddefinitions $end
$comment Show the parameter values. $end
$dumpall
b0 2
b10 1
b1 0
$end
#0
$dumpvars
b0 5
b0 4
b0 3
b0 /
b0 .
b0 -
b0 ,
b0 +
b0 *
b0 )
b0 (
b0 '
b0 &
b0 %
1$
b0 #
0"
b0 !
$end
#5000
1"
#10000
b101 !
b101 '
b101 /
b11 +
b11 ,
b10 *
b10 -
0"
b11100 #
b11100 %
0$
#15000
b1 &
b1 3
1"
#20000
b1 )
b1 .
b1 5
b10 !
b10 '
b10 /
b1 (
b1 4
b1 *
b1 -
0"
b111010 #
b111010 %
#25000
b10 &
b10 3
1"
#30000
b10 )
b10 .
b10 5
b0 !
b0 '
b0 /
b10 (
b10 4
b10 +
b10 ,
0"
b1010010 #
b1010010 %
#35000
b0 &
b0 3
1"
#40000
b11 )
b11 .
b11 5
b11 !
b11 '
b11 /
b11 (
b11 4
b11 +
b11 ,
0"
b1111010 #
b1111010 %
#45000
b1 &
b1 3
1"
